heritage_insight/__init__.py
heritage_insight/main.py
heritage_insight/prompts.py
heritage_insight-2025.12.21201637.dist-info/METADATA
heritage_insight-2025.12.21201637.dist-info/WHEEL
heritage_insight-2025.12.21201637.dist-info/top_level.txt
heritage_insight-2025.12.21201637.dist-info/RECORD
