Metadata-Version: 2.4
Name: heritage-insight
Version: 2025.12.21201637
Summary: Generates structured summaries, timelines, and thematic insights from historical or cultural texts using pattern matching and language models.
Author-email: heritage-insight <hi@eugene.plus>
License: MIT
Project-URL: Homepage, https://github.com/chigwell/heritage-insight
Requires-Python: >=3.9
Requires-Dist: langchain-llm7>=0.0.0
Requires-Dist: llmatch-messages>=0.0.0
Requires-Dist: langchain-core>=0.3.0
